src/ALU.sv
module ALU(
    input logic signed [31:0] A,
    input logic signed [31:0] B,

    input logic [3:0] ALUOp,

    output logic signed [31:0] ALURes = 0
);

    // It executes each time any input changes
    always @* begin
        case(ALUOp)
            4'b0000: ALURes = A + B; // ADD
            4'b1000: ALURes = A - B; // SUB
            4'b0001: ALURes = A << B; // SLL
            4'b0010: ALURes = A < B; // SLT
            4'b0011: ALURes = $unsigned(A) < $unsigned(B); // SLTU
            4'b0100: ALURes = A ^ B; // XOR
            4'b0101: ALURes = A >> B; // SRL
            4'b1101: ALURes = A >>> B; // SRA
            4'b0110: ALURes = A | B; // OR
            4'b0111: ALURes = A & B; // AND
            4'b1001: ALURes = B;
        endcase
    end
endmodule

tb/ALU_tb.sv
module ALU_tb;
    // Señales del testbench
    logic signed [31:0] A;
    logic signed [31:0] B;
    logic [3:0] ALUOp;
    logic signed [31:0] ALURes;
    
    // Instanciar el DUT (Device Under Test)
    ALU dut (
        .A(A),
        .B(B),
        .ALUOp(ALUOp),
        .ALURes(ALURes)
    );
    
    // Variables para verificación
    logic signed [31:0] expected;
    integer errors = 0;
    integer tests = 0;
    
    // Tarea para verificar resultados
    task check_result(input logic signed [31:0] exp, input string operation);
        tests++;
        if (ALURes !== exp) begin
            $display("ERROR en %s: A=%0d, B=%0d, Esperado=%0d, Obtenido=%0d", 
                     operation, A, B, exp, ALURes);
            errors++;
        end else begin
            $display("OK: %s - A=%0d, B=%0d, Resultado=%0d", operation, A, B, ALURes);
        end
    endtask

    // Inicialización de la simulación - Wavetrace
    initial begin
        $dumpfile("ALU_tb.vcd");    
        $dumpvars(0, ALU_tb);   
    end
    
    initial begin

        $display("=== Iniciando simulación del ALU ===\n");
        
        // Test 1: ADD (0000)
        $display("========== Test ADD (0000) ==========");
        ALUOp = 4'b0000;
        A = 32'h0000000F; B = 32'h0000000A; #10;  // 15 + 10
        check_result(32'h00000019, "ADD: 15 + 10");
        
        A = 32'hFFFFFFF1; B = 32'h0000000A; #10;  // -15 + 10
        check_result(32'hFFFFFFFB, "ADD: -15 + 10");
        
        // Test 2: SUB (1000)
        $display("========== Test SUB (1000) ==========");
        ALUOp = 4'b1000;
        A = 32'h00000014; B = 32'h00000005; #10;  // 20 - 5
        check_result(32'h0000000F, "SUB: 20 - 5");
        
        A = 32'h00000005; B = 32'h00000014; #10;  // 5 - 20
        check_result(32'hFFFFFFF1, "SUB: 5 - 20");
        
        // Test 3: SLL - Shift Left Logical (0001)
        $display("========== Test SLL (0001) - Desplazamiento a la izquierda ==========");
        ALUOp = 4'b0001;
        A = 32'h00000004; B = 32'h00000002; #10;  // 0100 << 2 = 10000
        check_result(32'h00000010, "SLL: 4 << 2");
        
        A = 32'h00000001; B = 32'h00000003; #10;  // 0001 << 3 = 1000
        check_result(32'h00000008, "SLL: 1 << 3");
        
        // Test 4: SLT - Set Less Than (0010)
        $display("========== Test SLT (0010) - Comparación con signo ==========");
        ALUOp = 4'b0010;
        A = 32'h00000005; B = 32'h0000000A; #10;  // 5 < 10 = 1
        check_result(32'h00000001, "SLT: 5 < 10");
        
        A = 32'h0000000A; B = 32'h00000005; #10;  // 10 < 5 = 0
        check_result(32'h00000000, "SLT: 10 < 5");
        
        A = 32'hFFFFFFFB; B = 32'h00000005; #10;  // -5 < 5 = 1
        check_result(32'h00000001, "SLT: -5 < 5");
        
        // Test 5: SLTU - Set Less Than Unsigned (0011)
        $display("========== Test SLTU (0011) - Comparación sin signo ==========");
        ALUOp = 4'b0011;
        A = 32'h00000005; B = 32'h0000000A; #10;  // 5 < 10 = 1
        check_result(32'h00000001, "SLTU: 5 < 10");
        
        A = 32'hFFFFFFFF; B = 32'h0000000A; #10;  // -1 (como unsigned es muy grande) < 10 = 0
        check_result(32'h00000000, "SLTU: 0xFFFFFFFF < 10 (unsigned)");
        
        // Test 6: XOR (0100)
        $display("========== Test XOR (0100) - OR exclusivo ==========");
        ALUOp = 4'b0100;
        A = 32'hAAAAAAAA; B = 32'h55555555; #10;  // Patrón alternado
        check_result(32'hFFFFFFFF, "XOR: 0xAAAAAAAA ^ 0x55555555");
        
        A = 32'hF0F0F0F0; B = 32'h0F0F0F0F; #10;
        check_result(32'hFFFFFFFF, "XOR: 0xF0F0F0F0 ^ 0x0F0F0F0F");
        
        // Test 7: SRL - Shift Right Logical (0101)
        $display("========== Test SRL (0101) - Desplazamiento lógico a la derecha ==========");
        ALUOp = 4'b0101;
        A = 32'h00000010; B = 32'h00000002; #10;  // 16 >> 2 = 4
        check_result(32'h00000004, "SRL: 16 >> 2");
        
        A = 32'hFFFFFFFF; B = 32'h00000004; #10;  // Rellena con 0s
        check_result(32'h0FFFFFFF, "SRL: 0xFFFFFFFF >> 4 (lógico)");
        
        // Test 8: SRA - Shift Right Arithmetic (1101)
        $display("========== Test SRA (1101) - Desplazamiento aritmético a la derecha ==========");
        ALUOp = 4'b1101;
        A = 32'h00000010; B = 32'h00000002; #10;  // 16 >> 2 = 4
        check_result(32'h00000004, "SRA: 16 >> 2 (positivo)");
        
        A = 32'hFFFFFFF0; B = 32'h00000002; #10;  // -16 >> 2 = -4 (mantiene signo)
        check_result(32'hFFFFFFFC, "SRA: -16 >> 2 (negativo, mantiene signo)");
        
        // Test 9: OR (0110)
        $display("========== Test OR (0110) - OR bit a bit ==========");
        ALUOp = 4'b0110;
        A = 32'hAAAAAAAA; B = 32'h55555555; #10;
        check_result(32'hFFFFFFFF, "OR: 0xAAAAAAAA | 0x55555555");
        
        A = 32'hF0000000; B = 32'h0000000F; #10;
        check_result(32'hF000000F, "OR: 0xF0000000 | 0x0000000F");
        
        // Test 10: AND (0111)
        $display("========== Test AND (0111) - AND bit a bit ==========");
        ALUOp = 4'b0111;
        A = 32'hFFFFFFFF; B = 32'h55555555; #10;
        check_result(32'h55555555, "AND: 0xFFFFFFFF & 0x55555555");
        
        A = 32'hF0F0F0F0; B = 32'hFFFF0000; #10;
        check_result(32'hF0F00000, "AND: 0xF0F0F0F0 & 0xFFFF0000");
        
        // Test 11: Pass B (1001)
        $display("========== Test Pass B (1001) - Pasar valor de B ==========");
        ALUOp = 4'b1001;
        A = 32'h00000064; B = 32'h00000032; #10;  // 100, 50
        check_result(32'h00000032, "Pass B: Resultado = B (50)");
        
        A = 32'h00000000; B = 32'hFFFFFFE7; #10;  // 0, -25
        check_result(32'hFFFFFFE7, "Pass B: Resultado = B (-25)");
        
        // Resumen
        $display("\n=== Resumen de la simulación ===");
        $display("Tests ejecutados: %0d", tests);
        $display("Tests exitosos: %0d", tests - errors);
        $display("Errores: %0d", errors);
        
        if (errors == 0)
            $display("\n¡Todos los tests pasaron exitosamente!");
        else
            $display("\n¡Atención! Se encontraron %0d errores.", errors);
        
        $finish;
    end
    
endmodule

sim/ALU_tb.vcd
$date
	Wed Oct 22 15:47:19 2025
$end
$version
	Icarus Verilog
$end
$timescale
	1s
$end
$scope module ALU_tb $end
$var wire 32 ! ALURes [31:0] $end
$var reg 32 " A [31:0] $end
$var reg 4 # ALUOp [3:0] $end
$var reg 32 $ B [31:0] $end
$var integer 32 % errors [31:0] $end
$var integer 32 & tests [31:0] $end
$scope module dut $end
$var wire 32 ' A [31:0] $end
$var wire 4 ( ALUOp [3:0] $end
$var wire 32 ) B [31:0] $end
$var reg 32 * ALURes [31:0] $end
$upscope $end
$scope task check_result $end
$var reg 32 + exp [31:0] $end
$upscope $end
$upscope $end
$enddefinitions $end
$comment Show the parameter values. $end
$dumpall
$end
#0
$dumpvars
bx +
b11001 *
b1010 )
b0 (
b1111 '
b0 &
b0 %
b1010 $
b0 #
b1111 "
b11001 !
$end
#10
b11111111111111111111111111111011 !
b11111111111111111111111111111011 *
b11111111111111111111111111110001 "
b11111111111111111111111111110001 '
b1 &
b11001 +
#20
b1111 !
b1111 *
b101 $
b101 )
b10100 "
b10100 '
b1000 #
b1000 (
b10 &
b11111111111111111111111111111011 +
#30
b11111111111111111111111111110001 !
b11111111111111111111111111110001 *
b10100 $
b10100 )
b101 "
b101 '
b11 &
b1111 +
#40
b10000 !
b10000 *
b10 $
b10 )
b100 "
b100 '
b1 #
b1 (
b100 &
b11111111111111111111111111110001 +
#50
b1000 !
b1000 *
b11 $
b11 )
b1 "
b1 '
b101 &
b10000 +
#60
b1 !
b1 *
b1010 $
b1010 )
b101 "
b101 '
b10 #
b10 (
b110 &
b1000 +
#70
b0 !
b0 *
b101 $
b101 )
b1010 "
b1010 '
b111 &
b1 +
#80
b1 !
b1 *
b11111111111111111111111111111011 "
b11111111111111111111111111111011 '
b1000 &
b0 +
#90
b1010 $
b1010 )
b101 "
b101 '
b11 #
b11 (
b1001 &
b1 +
#100
b0 !
b0 *
b11111111111111111111111111111111 "
b11111111111111111111111111111111 '
b1010 &
#110
b11111111111111111111111111111111 !
b11111111111111111111111111111111 *
b1010101010101010101010101010101 $
b1010101010101010101010101010101 )
b10101010101010101010101010101010 "
b10101010101010101010101010101010 '
b100 #
b100 (
b1011 &
b0 +
#120
b1111000011110000111100001111 $
b1111000011110000111100001111 )
b11110000111100001111000011110000 "
b11110000111100001111000011110000 '
b1100 &
b11111111111111111111111111111111 +
#130
b100 !
b100 *
b10 $
b10 )
b10000 "
b10000 '
b101 #
b101 (
b1101 &
#140
b1111111111111111111111111111 !
b1111111111111111111111111111 *
b100 $
b100 )
b11111111111111111111111111111111 "
b11111111111111111111111111111111 '
b1110 &
b100 +
#150
b100 !
b100 *
b10 $
b10 )
b10000 "
b10000 '
b1101 #
b1101 (
b1111 &
b1111111111111111111111111111 +
#160
b11111111111111111111111111111100 !
b11111111111111111111111111111100 *
b11111111111111111111111111110000 "
b11111111111111111111111111110000 '
b10000 &
b100 +
#170
b11111111111111111111111111111111 !
b11111111111111111111111111111111 *
b1010101010101010101010101010101 $
b1010101010101010101010101010101 )
b10101010101010101010101010101010 "
b10101010101010101010101010101010 '
b110 #
b110 (
b10001 &
b11111111111111111111111111111100 +
#180
b11110000000000000000000000001111 !
b11110000000000000000000000001111 *
b1111 $
b1111 )
b11110000000000000000000000000000 "
b11110000000000000000000000000000 '
b10010 &
b11111111111111111111111111111111 +
#190
b1010101010101010101010101010101 !
b1010101010101010101010101010101 *
b1010101010101010101010101010101 $
b1010101010101010101010101010101 )
b11111111111111111111111111111111 "
b11111111111111111111111111111111 '
b111 #
b111 (
b10011 &
b11110000000000000000000000001111 +
#200
b11110000111100000000000000000000 !
b11110000111100000000000000000000 *
b11111111111111110000000000000000 $
b11111111111111110000000000000000 )
b11110000111100001111000011110000 "
b11110000111100001111000011110000 '
b10100 &
b1010101010101010101010101010101 +
#210
b110010 !
b110010 *
b110010 $
b110010 )
b1100100 "
b1100100 '
b1001 #
b1001 (
b10101 &
b11110000111100000000000000000000 +
#220
b11111111111111111111111111100111 !
b11111111111111111111111111100111 *
b11111111111111111111111111100111 $
b11111111111111111111111111100111 )
b0 "
b0 '
b10110 &
b110010 +
#230
b10111 &
b11111111111111111111111111100111 +
