src/ALUBSrcMux.sv
module ALUBSrcMux(
    input logic signed [31:0] ru_rs2,
    input logic signed [31:0] Imm_ext,
    input logic sel,

    output logic signed [31:0] b
);
    always @(*) begin
        if (sel)
            b = Imm_ext;
        else
            b = ru_rs2;
    end
endmodule

tb/ALUBSrcMux_tb.sv
module ALUBSrcMux_tb;
    // Señales del testbench
    logic signed [31:0] ru_rs2;
    logic signed [31:0] Imm_ext;
    logic sel;
    logic signed [31:0] b;
    
    // Instanciar el DUT
    ALUBSrcMux dut (
        .ru_rs2(ru_rs2),
        .Imm_ext(Imm_ext),
        .sel(sel),
        .b(b)
    );
    
    // Variables para verificación
    integer errors = 0;
    integer tests = 0;
    
    // Inicialización para wavetrace
    initial begin
        $dumpfile("sim/ALUBSrcMux_tb.vcd");
        $dumpvars(0, ALUBSrcMux_tb);
    end
    
    // Tarea para verificar resultado
    task check_result(input [31:0] rs2_val, input [31:0] imm_val, 
                     input sel_val, input [31:0] expected, input string test_name);
        tests++;
        ru_rs2 = rs2_val;
        Imm_ext = imm_val;
        sel = sel_val;
        #10; // Esperar a que se propague
        $display("Test %0d: %s", tests, test_name);
        $display("  ru_rs2   = 0x%h", rs2_val);
        $display("  Imm_ext  = 0x%h", imm_val);
        $display("  SEL      = %b (%s)", sel_val, sel_val ? "Imm_ext" : "ru_rs2");
        $display("  Esperado = 0x%h", expected);
        $display("  Obtenido = 0x%h", b);
        if (b !== expected) begin
            $display("  ERROR: No coincide");
            errors++;
        end else begin
            $display("  OK");
        end
        $display("");
    endtask
    
    // Secuencia de pruebas
    initial begin
        ru_rs2 = 0;
        Imm_ext = 0;
        sel = 0;
        
        $display("========================================");
        $display("=== Iniciando simulacion ALUBSrcMux ===");
        $display("========================================\n");
        
        #10;
        
        // Test 1: Seleccionar ru_rs2 (sel=0)
        $display("========== Test 1: Seleccionar ru_rs2 ==========");
        check_result(32'h00000014, 32'h00000064, 1'b0, 32'h00000014, "Usar ru_rs2");
        
        // Test 2: Seleccionar Imm_ext (sel=1)
        $display("========== Test 2: Seleccionar Imm_ext ==========");
        check_result(32'h00000014, 32'h00000064, 1'b1, 32'h00000064, "Usar Imm_ext");
        
        // Test 3: Seleccionar ru_rs2 con valor negativo (sel=0)
        $display("========== Test 3: ru_rs2 negativo ==========");
        check_result(32'hFFFFFFE0, 32'h00000010, 1'b0, 32'hFFFFFFE0, "Usar ru_rs2 negativo");
        
        // Test 4: Seleccionar Imm_ext con valor negativo (sel=1)
        $display("========== Test 4: Imm_ext negativo ==========");
        check_result(32'h00000050, 32'hFFFFFFF0, 1'b1, 32'hFFFFFFF0, "Usar Imm_ext negativo");
        
        // Test 5: Seleccionar ru_rs2 con valor grande (sel=0)
        $display("========== Test 5: ru_rs2 valor grande ==========");
        check_result(32'h7FFFFFFF, 32'h00000001, 1'b0, 32'h7FFFFFFF, "Usar ru_rs2 grande");
        
        // Test 6: Seleccionar Imm_ext con offset grande (sel=1)
        $display("========== Test 6: Imm_ext offset grande ==========");
        check_result(32'h00000100, 32'h00000FFF, 1'b1, 32'h00000FFF, "Usar Imm_ext grande");
        
        // Test 7: Seleccionar ru_rs2 con cero (sel=0)
        $display("========== Test 7: ru_rs2 cero ==========");
        check_result(32'h00000000, 32'h00000020, 1'b0, 32'h00000000, "Usar ru_rs2 cero");
        
        // Test 8: Seleccionar Imm_ext con cero (sel=1)
        $display("========== Test 8: Imm_ext cero ==========");
        check_result(32'h00000ABC, 32'h00000000, 1'b1, 32'h00000000, "Usar Imm_ext cero");
        
        // Resumen final
        $display("========================================");
        $display("=== Resumen de la simulacion ===");
        $display("Tests ejecutados: %0d", tests);
        $display("Tests exitosos: %0d", tests - errors);
        $display("Errores: %0d", errors);
        $display("========================================");
        
        if (errors == 0)
            $display("Todos los tests pasaron exitosamente");
        else
            $display("Se encontraron %0d errores", errors);
        
        $finish;
    end
    
endmodule

sim/ALUBSrcMux_tb.vcd
$date
	Wed Oct 29 23:35:26 2025
$end
$version
	Icarus Verilog
$end
$timescale
	1s
$end
$scope module ALUBSrcMux_tb $end
$var wire 32 ! b [31:0] $end
$var reg 32 " Imm_ext [31:0] $end
$var reg 32 # ru_rs2 [31:0] $end
$var reg 1 $ sel $end
$var integer 32 % errors [31:0] $end
$var integer 32 & tests [31:0] $end
$scope module dut $end
$var wire 32 ' Imm_ext [31:0] $end
$var wire 32 ( ru_rs2 [31:0] $end
$var wire 1 $ sel $end
$var reg 32 ) b [31:0] $end
$upscope $end
$scope task check_result $end
$var reg 32 * expected [31:0] $end
$var reg 32 + imm_val [31:0] $end
$var reg 32 , rs2_val [31:0] $end
$var reg 1 - sel_val $end
$upscope $end
$upscope $end
$enddefinitions $end
$comment Show the parameter values. $end
$dumpall
$end
#0
$dumpvars
x-
bx ,
bx +
bx *
b0 )
b0 (
b0 '
b0 &
b0 %
0$
b0 #
b0 "
b0 !
$end
#10
b10100 !
b10100 )
b1100100 "
b1100100 '
b10100 #
b10100 (
b1 &
b10100 *
0-
b1100100 +
b10100 ,
#20
b1100100 !
b1100100 )
1$
b10 &
b1100100 *
1-
#30
b11111111111111111111111111100000 !
b11111111111111111111111111100000 )
0$
b10000 "
b10000 '
b11111111111111111111111111100000 #
b11111111111111111111111111100000 (
b11 &
b11111111111111111111111111100000 *
0-
b10000 +
b11111111111111111111111111100000 ,
#40
b11111111111111111111111111110000 !
b11111111111111111111111111110000 )
1$
b11111111111111111111111111110000 "
b11111111111111111111111111110000 '
b1010000 #
b1010000 (
b100 &
b11111111111111111111111111110000 *
1-
b11111111111111111111111111110000 +
b1010000 ,
#50
b1111111111111111111111111111111 !
b1111111111111111111111111111111 )
0$
b1 "
b1 '
b1111111111111111111111111111111 #
b1111111111111111111111111111111 (
b101 &
b1111111111111111111111111111111 *
0-
b1 +
b1111111111111111111111111111111 ,
#60
b111111111111 !
b111111111111 )
1$
b111111111111 "
b111111111111 '
b100000000 #
b100000000 (
b110 &
b111111111111 *
1-
b111111111111 +
b100000000 ,
#70
b0 !
b0 )
0$
b100000 "
b100000 '
b0 #
b0 (
b111 &
b0 *
0-
b100000 +
b0 ,
#80
1$
b0 "
b0 '
b101010111100 #
b101010111100 (
b1000 &
1-
b0 +
b101010111100 ,
