src/ControlUnit.sv
module ControlUnit (
    input  logic [6:0] OpCode,
    input  logic [2:0] Funct3,
    input  logic [6:0] Funct7,

    // Señales de control del datapath
    output logic       RUWr,
    output logic [1:0] RUDataWrSrc,

    output logic       ALUASrc,
    output logic       ALUBSrc,
    output logic [3:0] ALUOp,

    output logic       DMWr,
    output logic [2:0] DMCtrl,

    output logic [2:0] ImmSrc,
    output logic [4:0] BrOp
);

    always @(*) begin

        // Reset de todas las señales
        RUWr        = 0;
        RUDataWrSrc = 2'b00;
        ALUASrc     = 0;
        ALUBSrc     = 0;
        ALUOp       = 4'b0000;
        DMWr        = 0;
        DMCtrl      = 3'b000;
        ImmSrc      = 3'b000;
        BrOp        = 5'b00000;

        case (OpCode)

        // ============================================
        //  TYPE R
        // ============================================
        7'b0110011: begin
            RUWr = 1;
            ALUASrc = 0;
            ALUBSrc = 0;
            RUDataWrSrc = 2'b00; // from ALU
            ImmSrc = 3'b000; // not used

            // ALU operation determined by funct3/funct7
            case ({Funct7, Funct3})
                10'b0000000_000: ALUOp = 4'b0000; // ADD
                10'b0100000_000: ALUOp = 4'b1000; // SUB
                10'b0000000_001: ALUOp = 4'b0001; // SLL
                10'b0000000_010: ALUOp = 4'b0010; // SLT
                10'b0000000_011: ALUOp = 4'b0011; // SLTU
                10'b0000000_100: ALUOp = 4'b0100; // XOR
                10'b0000000_101: ALUOp = 4'b0101; // SRL
                10'b0100000_101: ALUOp = 4'b1101; // SRA
                10'b0000000_110: ALUOp = 4'b0110; // OR
                10'b0000000_111: ALUOp = 4'b0111; // AND
                
                default:          ALUOp = 4'b0000;
            endcase
        end

        // ============================================
        //  TYPE I
        // ============================================
        7'b0010011: begin
            RUWr = 1;
            ALUASrc = 0;
            ALUBSrc = 1; // immediate
            RUDataWrSrc = 2'b00; 
            ImmSrc = 3'b000; // I-type

            case (Funct3)
                3'b000: ALUOp = 4'b0000; // ADDI
                3'b001: ALUOp = 4'b0001; // SLLI
                3'b010: ALUOp = 4'b0010; // SLTI
                3'b011: ALUOp = 4'b0011; // SLTIU
                3'b100: ALUOp = 4'b0100; // XORI
                3'b101: ALUOp = 4'b0101; // SRLI/SRAI
                3'b110: ALUOp = 4'b0110; // ORI
                3'b111: ALUOp = 4'b0111; // ANDI
                
            endcase
        end

        // ============================================
        // LOAD 
        // ============================================
        7'b0000011: begin
            RUWr        = 1;
            ALUASrc     = 0;
            ALUBSrc     = 1;
            RUDataWrSrc = 2'b01; // Memory
            ImmSrc      = 3'b000; // I-type
            DMWr        = 0;

            DMCtrl = Funct3; // memory access type

            ALUOp = 4'b0000; // address = rs1 + imm
        end

        // ============================================
        // STORE 
        // ============================================
        7'b0100011: begin
            RUWr    = 0;
            ALUASrc = 0;
            ALUBSrc = 1;
            ImmSrc  = 3'b001; // S-type

            DMWr = 1;
            DMCtrl = Funct3;

            ALUOp = 4'b0000;
        end

        // ============================================
        // BRANCH
        // ============================================
        7'b1100011: begin
            RUWr = 0;
            ALUASrc = 0;
            ALUBSrc = 0;

            ImmSrc = 3'b101; // B-type

            case (Funct3)
                3'b000: BrOp = 5'b01000;   // BEQ
                3'b001: BrOp = 5'b01001;   // BNE
                3'b100: BrOp = 5'b01100;   // BLT
                3'b101: BrOp = 5'b01101;   // BGE
                3'b110: BrOp = 5'b01110;   // BLTU
                3'b111: BrOp = 5'b01111;   // BGEU
            endcase
        end

        // ============================================
        // JAL
        // ============================================
        7'b1101111: begin
            RUWr        = 1;
            RUDataWrSrc = 2'b10; // PC+4
            ImmSrc      = 3'b110; // J-type
            BrOp        = 5'b10000; // unconditional
        end

        // ============================================
        // JALR
        // ============================================
        7'b1100111: begin
            RUWr        = 1;
            RUDataWrSrc = 2'b10; 
            ImmSrc      = 3'b000;
            BrOp        = 5'b10000;
        end

        // ============================================
        // LUI
        // ============================================
        7'b0110111: begin
            RUWr = 1;
            RUDataWrSrc = 2'b11; // immediate extended
            ImmSrc = 3'b010; // U-type
        end

        // AUIPC
        7'b0010111: begin
            RUWr = 1;
            RUDataWrSrc = 2'b00;
            ImmSrc = 3'b010;
            ALUASrc = 1; // PC
            ALUBSrc = 1; // immediate
            ALUOp = 4'b0000;
        end

        endcase
    end

endmodule

tb/ControlUnit_tb.sv
`timescale 1ns/1ps

module ControlUnit_tb;

    // Señales de entrada
    logic [6:0] OpCode;
    logic [2:0] Funct3;
    logic [6:0] Funct7;
    
    // Señales de salida
    logic       RUWr;
    logic [1:0] RUDataWrSrc;
    logic       ALUASrc;
    logic       ALUBSrc;
    logic [3:0] ALUOp;
    logic       DMWr;
    logic [2:0] DMCtrl;
    logic [2:0] ImmSrc;
    logic [4:0] BrOp;
    
    // Instancia del módulo
    ControlUnit uut (
        .OpCode(OpCode),
        .Funct3(Funct3),
        .Funct7(Funct7),
        .RUWr(RUWr),
        .RUDataWrSrc(RUDataWrSrc),
        .ALUASrc(ALUASrc),
        .ALUBSrc(ALUBSrc),
        .ALUOp(ALUOp),
        .DMWr(DMWr),
        .DMCtrl(DMCtrl),
        .ImmSrc(ImmSrc),
        .BrOp(BrOp)
    );
    
    integer errors = 0;
    integer tests = 0;

    initial begin
        $dumpfile("sim/ControlUnit_tb.vcd");
        $dumpvars(0, ControlUnit_tb);
    end
    
    // Task para verificar señales
    task check_signals(
        input string test_name,
        input logic exp_RUWr,
        input logic [1:0] exp_RUDataWrSrc,
        input logic exp_ALUASrc,
        input logic exp_ALUBSrc,
        input logic [3:0] exp_ALUOp,
        input logic exp_DMWr,
        input logic [2:0] exp_DMCtrl,
        input logic [2:0] exp_ImmSrc,
        input logic [4:0] exp_BrOp
    );
        tests++;
        #1;
        
        if (RUWr !== exp_RUWr || RUDataWrSrc !== exp_RUDataWrSrc || 
            ALUASrc !== exp_ALUASrc || ALUBSrc !== exp_ALUBSrc ||
            ALUOp !== exp_ALUOp || DMWr !== exp_DMWr || 
            DMCtrl !== exp_DMCtrl || ImmSrc !== exp_ImmSrc || BrOp !== exp_BrOp) begin
            
            $display("ERROR: %s", test_name);
            $display("   OpCode: 0x%h, Funct3: 0x%h, Funct7: 0x%h", OpCode, Funct3, Funct7);
            
            if (RUWr !== exp_RUWr)
                $display("   RUWr: Expected %b, Got %b", exp_RUWr, RUWr);
            if (RUDataWrSrc !== exp_RUDataWrSrc)
                $display("   RUDataWrSrc: Expected %b, Got %b", exp_RUDataWrSrc, RUDataWrSrc);
            if (ALUASrc !== exp_ALUASrc)
                $display("   ALUASrc: Expected %b, Got %b", exp_ALUASrc, ALUASrc);
            if (ALUBSrc !== exp_ALUBSrc)
                $display("   ALUBSrc: Expected %b, Got %b", exp_ALUBSrc, ALUBSrc);
            if (ALUOp !== exp_ALUOp)
                $display("   ALUOp: Expected 0x%h, Got 0x%h", exp_ALUOp, ALUOp);
            if (DMWr !== exp_DMWr)
                $display("   DMWr: Expected %b, Got %b", exp_DMWr, DMWr);
            if (DMCtrl !== exp_DMCtrl)
                $display("   DMCtrl: Expected %b, Got %b", exp_DMCtrl, DMCtrl);
            if (ImmSrc !== exp_ImmSrc)
                $display("   ImmSrc: Expected %b, Got %b", exp_ImmSrc, ImmSrc);
            if (BrOp !== exp_BrOp)
                $display("   BrOp: Expected %b, Got %b", exp_BrOp, BrOp);
            
            errors++;
        end else begin
            $display("PASS: %s", test_name);
        end
    endtask
    
    initial begin
        $display("\n========================================");
        $display("  ControlUnit Testbench");
        $display("========================================\n");
        
        // ==================== R-TYPE INSTRUCTIONS ====================
        $display("--- R-TYPE INSTRUCTIONS ---\n");
        
        // Test 1: ADD
        OpCode = 7'b0110011; Funct3 = 3'b000; Funct7 = 7'b0000000;
        #10 check_signals("ADD", 1, 2'b00, 0, 0, 4'b0000, 0, 3'b000, 3'b000, 5'b00000);
        
        // Test 2: SUB
        OpCode = 7'b0110011; Funct3 = 3'b000; Funct7 = 7'b0100000;
        #10 check_signals("SUB", 1, 2'b00, 0, 0, 4'b1000, 0, 3'b000, 3'b000, 5'b00000);
        
        // Test 3: SLL
        OpCode = 7'b0110011; Funct3 = 3'b001; Funct7 = 7'b0000000;
        #10 check_signals("SLL", 1, 2'b00, 0, 0, 4'b0001, 0, 3'b000, 3'b000, 5'b00000);
        
        // Test 4: SLT
        OpCode = 7'b0110011; Funct3 = 3'b010; Funct7 = 7'b0000000;
        #10 check_signals("SLT", 1, 2'b00, 0, 0, 4'b0010, 0, 3'b000, 3'b000, 5'b00000);
        
        // Test 5: SLTU
        OpCode = 7'b0110011; Funct3 = 3'b011; Funct7 = 7'b0000000;
        #10 check_signals("SLTU", 1, 2'b00, 0, 0, 4'b0011, 0, 3'b000, 3'b000, 5'b00000);
        
        // Test 6: XOR
        OpCode = 7'b0110011; Funct3 = 3'b100; Funct7 = 7'b0000000;
        #10 check_signals("XOR", 1, 2'b00, 0, 0, 4'b0100, 0, 3'b000, 3'b000, 5'b00000);
        
        // Test 7: SRL
        OpCode = 7'b0110011; Funct3 = 3'b101; Funct7 = 7'b0000000;
        #10 check_signals("SRL", 1, 2'b00, 0, 0, 4'b0101, 0, 3'b000, 3'b000, 5'b00000);
        
        // Test 8: SRA
        OpCode = 7'b0110011; Funct3 = 3'b101; Funct7 = 7'b0100000;
        #10 check_signals("SRA", 1, 2'b00, 0, 0, 4'b1101, 0, 3'b000, 3'b000, 5'b00000);
        
        // Test 9: OR
        OpCode = 7'b0110011; Funct3 = 3'b110; Funct7 = 7'b0000000;
        #10 check_signals("OR", 1, 2'b00, 0, 0, 4'b0110, 0, 3'b000, 3'b000, 5'b00000);
        
        // Test 10: AND
        OpCode = 7'b0110011; Funct3 = 3'b111; Funct7 = 7'b0000000;
        #10 check_signals("AND", 1, 2'b00, 0, 0, 4'b0111, 0, 3'b000, 3'b000, 5'b00000);
        
        // ==================== I-TYPE INSTRUCTIONS ====================
        $display("\n--- I-TYPE INSTRUCTIONS ---\n");
        
        // Test 11: ADDI
        OpCode = 7'b0010011; Funct3 = 3'b000; Funct7 = 7'b0000000;
        #10 check_signals("ADDI", 1, 2'b00, 0, 1, 4'b0000, 0, 3'b000, 3'b000, 5'b00000);
        
        // Test 12: SLLI
        OpCode = 7'b0010011; Funct3 = 3'b001; Funct7 = 7'b0000000;
        #10 check_signals("SLLI", 1, 2'b00, 0, 1, 4'b0001, 0, 3'b000, 3'b000, 5'b00000);
        
        // Test 13: SLTI
        OpCode = 7'b0010011; Funct3 = 3'b010; Funct7 = 7'b0000000;
        #10 check_signals("SLTI", 1, 2'b00, 0, 1, 4'b0010, 0, 3'b000, 3'b000, 5'b00000);
        
        // Test 14: SLTIU
        OpCode = 7'b0010011; Funct3 = 3'b011; Funct7 = 7'b0000000;
        #10 check_signals("SLTIU", 1, 2'b00, 0, 1, 4'b0011, 0, 3'b000, 3'b000, 5'b00000);
        
        // Test 15: XORI
        OpCode = 7'b0010011; Funct3 = 3'b100; Funct7 = 7'b0000000;
        #10 check_signals("XORI", 1, 2'b00, 0, 1, 4'b0100, 0, 3'b000, 3'b000, 5'b00000);
        
        // Test 16: SRLI
        OpCode = 7'b0010011; Funct3 = 3'b101; Funct7 = 7'b0000000;
        #10 check_signals("SRLI", 1, 2'b00, 0, 1, 4'b0101, 0, 3'b000, 3'b000, 5'b00000);
        
        // Test 17: SRAI (nota: tu implementacion actual no distingue SRAI de SRLI)
        OpCode = 7'b0010011; Funct3 = 3'b101; Funct7 = 7'b0100000;
        #10 check_signals("SRAI", 1, 2'b00, 0, 1, 4'b0101, 0, 3'b000, 3'b000, 5'b00000);
        
        // Test 18: ORI
        OpCode = 7'b0010011; Funct3 = 3'b110; Funct7 = 7'b0000000;
        #10 check_signals("ORI", 1, 2'b00, 0, 1, 4'b0110, 0, 3'b000, 3'b000, 5'b00000);
        
        // Test 19: ANDI
        OpCode = 7'b0010011; Funct3 = 3'b111; Funct7 = 7'b0000000;
        #10 check_signals("ANDI", 1, 2'b00, 0, 1, 4'b0111, 0, 3'b000, 3'b000, 5'b00000);
        
        // ==================== LOAD INSTRUCTIONS ====================
        $display("\n--- LOAD INSTRUCTIONS ---\n");
        
        // Test 20: LB
        OpCode = 7'b0000011; Funct3 = 3'b000; Funct7 = 7'b0000000;
        #10 check_signals("LB", 1, 2'b01, 0, 1, 4'b0000, 0, 3'b000, 3'b000, 5'b00000);
        
        // Test 21: LH
        OpCode = 7'b0000011; Funct3 = 3'b001; Funct7 = 7'b0000000;
        #10 check_signals("LH", 1, 2'b01, 0, 1, 4'b0000, 0, 3'b001, 3'b000, 5'b00000);
        
        // Test 22: LW
        OpCode = 7'b0000011; Funct3 = 3'b010; Funct7 = 7'b0000000;
        #10 check_signals("LW", 1, 2'b01, 0, 1, 4'b0000, 0, 3'b010, 3'b000, 5'b00000);
        
        // Test 23: LBU
        OpCode = 7'b0000011; Funct3 = 3'b100; Funct7 = 7'b0000000;
        #10 check_signals("LBU", 1, 2'b01, 0, 1, 4'b0000, 0, 3'b100, 3'b000, 5'b00000);
        
        // Test 24: LHU
        OpCode = 7'b0000011; Funct3 = 3'b101; Funct7 = 7'b0000000;
        #10 check_signals("LHU", 1, 2'b01, 0, 1, 4'b0000, 0, 3'b101, 3'b000, 5'b00000);
        
        // ==================== STORE INSTRUCTIONS ====================
        $display("\n--- STORE INSTRUCTIONS ---\n");
        
        // Test 25: SB
        OpCode = 7'b0100011; Funct3 = 3'b000; Funct7 = 7'b0000000;
        #10 check_signals("SB", 0, 2'b00, 0, 1, 4'b0000, 1, 3'b000, 3'b001, 5'b00000);
        
        // Test 26: SH
        OpCode = 7'b0100011; Funct3 = 3'b001; Funct7 = 7'b0000000;
        #10 check_signals("SH", 0, 2'b00, 0, 1, 4'b0000, 1, 3'b001, 3'b001, 5'b00000);
        
        // Test 27: SW
        OpCode = 7'b0100011; Funct3 = 3'b010; Funct7 = 7'b0000000;
        #10 check_signals("SW", 0, 2'b00, 0, 1, 4'b0000, 1, 3'b010, 3'b001, 5'b00000);
        
        // ==================== BRANCH INSTRUCTIONS ====================
        $display("\n--- BRANCH INSTRUCTIONS ---\n");
        
        // Test 28: BEQ
        OpCode = 7'b1100011; Funct3 = 3'b000; Funct7 = 7'b0000000;
        #10 check_signals("BEQ", 0, 2'b00, 0, 0, 4'b0000, 0, 3'b000, 3'b101, 5'b01000);
        
        // Test 29: BNE
        OpCode = 7'b1100011; Funct3 = 3'b001; Funct7 = 7'b0000000;
        #10 check_signals("BNE", 0, 2'b00, 0, 0, 4'b0000, 0, 3'b000, 3'b101, 5'b01001);
        
        // Test 30: BLT
        OpCode = 7'b1100011; Funct3 = 3'b100; Funct7 = 7'b0000000;
        #10 check_signals("BLT", 0, 2'b00, 0, 0, 4'b0000, 0, 3'b000, 3'b101, 5'b01100);
        
        // Test 31: BGE
        OpCode = 7'b1100011; Funct3 = 3'b101; Funct7 = 7'b0000000;
        #10 check_signals("BGE", 0, 2'b00, 0, 0, 4'b0000, 0, 3'b000, 3'b101, 5'b01101);
        
        // Test 32: BLTU
        OpCode = 7'b1100011; Funct3 = 3'b110; Funct7 = 7'b0000000;
        #10 check_signals("BLTU", 0, 2'b00, 0, 0, 4'b0000, 0, 3'b000, 3'b101, 5'b01110);
        
        // Test 33: BGEU
        OpCode = 7'b1100011; Funct3 = 3'b111; Funct7 = 7'b0000000;
        #10 check_signals("BGEU", 0, 2'b00, 0, 0, 4'b0000, 0, 3'b000, 3'b101, 5'b01111);
        
        // ==================== JUMP INSTRUCTIONS ====================
        $display("\n--- JUMP INSTRUCTIONS ---\n");
        
        // Test 34: JAL
        OpCode = 7'b1101111; Funct3 = 3'b000; Funct7 = 7'b0000000;
        #10 check_signals("JAL", 1, 2'b10, 0, 0, 4'b0000, 0, 3'b000, 3'b110, 5'b10000);
        
        // Test 35: JALR
        OpCode = 7'b1100111; Funct3 = 3'b000; Funct7 = 7'b0000000;
        #10 check_signals("JALR", 1, 2'b10, 0, 0, 4'b0000, 0, 3'b000, 3'b000, 5'b10000);
        
        // ==================== UPPER IMMEDIATE INSTRUCTIONS ====================
        $display("\n--- UPPER IMMEDIATE INSTRUCTIONS ---\n");
        
        // Test 36: LUI
        OpCode = 7'b0110111; Funct3 = 3'b000; Funct7 = 7'b0000000;
        #10 check_signals("LUI", 1, 2'b11, 0, 0, 4'b0000, 0, 3'b000, 3'b010, 5'b00000);
        
        // Test 37: AUIPC
        OpCode = 7'b0010111; Funct3 = 3'b000; Funct7 = 7'b0000000;
        #10 check_signals("AUIPC", 1, 2'b00, 1, 1, 4'b0000, 0, 3'b000, 3'b010, 5'b00000);
        
        // ==================== RESUMEN ====================
        $display("\n========================================");
        $display("  TEST SUMMARY");
        $display("========================================");
        $display("Total tests: %0d", tests);
        $display("Passed:      %0d", tests - errors);
        $display("Failed:      %0d", errors);
        
        if (errors == 0) begin
            $display("\nALL TESTS PASSED");
        end else begin
            $display("\nSOME TESTS FAILED");
        end
        $display("========================================\n");
        
        $finish;
    end

endmodule

sim/ControlUnit_tb.vcd
$date
	Wed Nov 26 13:19:00 2025
$end
$version
	Icarus Verilog
$end
$timescale
	1ps
$end
$scope module ControlUnit_tb $end
$var wire 1 ! RUWr $end
$var wire 2 " RUDataWrSrc [1:0] $end
$var wire 3 # ImmSrc [2:0] $end
$var wire 1 $ DMWr $end
$var wire 3 % DMCtrl [2:0] $end
$var wire 5 & BrOp [4:0] $end
$var wire 4 ' ALUOp [3:0] $end
$var wire 1 ( ALUBSrc $end
$var wire 1 ) ALUASrc $end
$var reg 3 * Funct3 [2:0] $end
$var reg 7 + Funct7 [6:0] $end
$var reg 7 , OpCode [6:0] $end
$var integer 32 - errors [31:0] $end
$var integer 32 . tests [31:0] $end
$scope module uut $end
$var wire 3 / Funct3 [2:0] $end
$var wire 7 0 Funct7 [6:0] $end
$var wire 7 1 OpCode [6:0] $end
$var reg 1 ) ALUASrc $end
$var reg 1 ( ALUBSrc $end
$var reg 4 2 ALUOp [3:0] $end
$var reg 5 3 BrOp [4:0] $end
$var reg 3 4 DMCtrl [2:0] $end
$var reg 1 $ DMWr $end
$var reg 3 5 ImmSrc [2:0] $end
$var reg 2 6 RUDataWrSrc [1:0] $end
$var reg 1 ! RUWr $end
$upscope $end
$scope task check_signals $end
$var reg 1 7 exp_ALUASrc $end
$var reg 1 8 exp_ALUBSrc $end
$var reg 4 9 exp_ALUOp [3:0] $end
$var reg 5 : exp_BrOp [4:0] $end
$var reg 3 ; exp_DMCtrl [2:0] $end
$var reg 1 < exp_DMWr $end
$var reg 3 = exp_ImmSrc [2:0] $end
$var reg 2 > exp_RUDataWrSrc [1:0] $end
$var reg 1 ? exp_RUWr $end
$upscope $end
$upscope $end
$enddefinitions $end
$comment Show the parameter values. $end
$dumpall
$end
#0
$dumpvars
x?
bx >
bx =
x<
bx ;
bx :
bx 9
x8
x7
b0 6
b0 5
b0 4
b0 3
b0 2
b110011 1
b0 0
b0 /
b0 .
b0 -
b110011 ,
b0 +
b0 *
0)
0(
b0 '
b0 &
b0 %
0$
b0 #
b0 "
1!
$end
#10000
b1 .
b0 :
b0 =
b0 ;
0<
b0 9
08
07
b0 >
1?
#11000
b1000 '
b1000 2
1!
b100000 +
b100000 0
#21000
b10 .
b1000 9
#22000
b1 '
b1 2
1!
b0 +
b0 0
b1 *
b1 /
#32000
b11 .
b1 9
#33000
b10 '
b10 2
1!
b10 *
b10 /
#43000
b100 .
b10 9
#44000
b11 '
b11 2
1!
b11 *
b11 /
#54000
b101 .
b11 9
#55000
b100 '
b100 2
1!
b100 *
b100 /
#65000
b110 .
b100 9
#66000
b101 '
b101 2
1!
b101 *
b101 /
#76000
b111 .
b101 9
#77000
b1101 '
b1101 2
1!
b100000 +
b100000 0
#87000
b1000 .
b1101 9
#88000
b110 '
b110 2
1!
b0 +
b0 0
b110 *
b110 /
#98000
b1001 .
b110 9
#99000
b111 '
b111 2
1!
b111 *
b111 /
#109000
b1010 .
b111 9
#110000
1(
b0 '
b0 2
1!
b0 *
b0 /
b10011 ,
b10011 1
#120000
b1011 .
b0 9
18
#121000
b1 '
b1 2
1(
1!
b1 *
b1 /
#131000
b1100 .
b1 9
#132000
b10 '
b10 2
1(
1!
b10 *
b10 /
#142000
b1101 .
b10 9
#143000
b11 '
b11 2
1(
1!
b11 *
b11 /
#153000
b1110 .
b11 9
#154000
b100 '
b100 2
1(
1!
b100 *
b100 /
#164000
b1111 .
b100 9
#165000
b101 '
b101 2
1(
1!
b101 *
b101 /
#175000
b10000 .
b101 9
#176000
b101 '
b101 2
1(
1!
b100000 +
b100000 0
#186000
b10001 .
#187000
b110 '
b110 2
1(
1!
b0 +
b0 0
b110 *
b110 /
#197000
b10010 .
b110 9
#198000
b111 '
b111 2
1(
1!
b111 *
b111 /
#208000
b10011 .
b111 9
#209000
b1 "
b1 6
b0 '
b0 2
1(
1!
b0 *
b0 /
b11 ,
b11 1
#219000
b10100 .
b0 9
b1 >
#220000
b1 %
b1 4
1(
b1 "
b1 6
1!
b1 *
b1 /
#230000
b10101 .
b1 ;
#231000
b10 %
b10 4
1(
b1 "
b1 6
1!
b10 *
b10 /
#241000
b10110 .
b10 ;
#242000
b100 %
b100 4
1(
b1 "
b1 6
1!
b100 *
b100 /
#252000
b10111 .
b100 ;
#253000
b101 %
b101 4
1(
b1 "
b1 6
1!
b101 *
b101 /
#263000
b11000 .
b101 ;
#264000
1$
b1 #
b1 5
b0 %
b0 4
1(
b0 "
b0 6
0!
b0 *
b0 /
b100011 ,
b100011 1
#274000
b11001 .
b1 =
b0 ;
1<
b0 >
0?
#275000
b1 %
b1 4
b1 #
b1 5
1$
1(
b1 *
b1 /
#285000
b11010 .
b1 ;
#286000
b1 #
b1 5
b10 %
b10 4
1$
1(
b10 *
b10 /
#296000
b11011 .
b10 ;
#297000
b1000 &
b1000 3
b101 #
b101 5
b0 %
b0 4
0$
0(
b0 *
b0 /
b1100011 ,
b1100011 1
#307000
b11100 .
b1000 :
b101 =
b0 ;
0<
08
#308000
b1001 &
b1001 3
b101 #
b101 5
b1 *
b1 /
#318000
b11101 .
b1001 :
#319000
b1100 &
b1100 3
b101 #
b101 5
b100 *
b100 /
#329000
b11110 .
b1100 :
#330000
b1101 &
b1101 3
b101 #
b101 5
b101 *
b101 /
#340000
b11111 .
b1101 :
#341000
b1110 &
b1110 3
b101 #
b101 5
b110 *
b110 /
#351000
b100000 .
b1110 :
#352000
b1111 &
b1111 3
b101 #
b101 5
b111 *
b111 /
#362000
b100001 .
b1111 :
#363000
b10 "
b10 6
1!
b10000 &
b10000 3
b110 #
b110 5
b0 *
b0 /
b1101111 ,
b1101111 1
#373000
b100010 .
b10000 :
b110 =
b10 >
1?
#374000
b10000 &
b10000 3
b0 #
b0 5
b10 "
b10 6
1!
b1100111 ,
b1100111 1
#384000
b100011 .
b0 =
#385000
b10 #
b10 5
b0 &
b0 3
b11 "
b11 6
1!
b110111 ,
b110111 1
#395000
b100100 .
b0 :
b10 =
b11 >
#396000
1(
1)
b10 #
b10 5
b0 "
b0 6
1!
b10111 ,
b10111 1
#406000
b100101 .
18
17
b0 >
