src/DataMemory.sv
module DataMemory #(
    parameter ADDR_WIDTH = 10   // 1024 palabras => 4 KB
)(
    input  logic [31:0] Address,
    input  logic [31:0] DataWr,
    input  logic        DMWr,
    input  logic [2:0]  DMCtrl,
    output logic [31:0] DataRd
);

    // Memoria de 32 bits por palabra
    logic [31:0] mem [0:(1<<ADDR_WIDTH)-1];

    // ------------------------------------------------------------
    //                   ESCRITURA (Store)
    // ------------------------------------------------------------
    always_comb begin
        if (DMWr) begin
            case (DMCtrl)
                3'b110: begin  // SB
                    case (Address[1:0])
                        2'b00: mem[Address[31:2]][7:0]   = DataWr[7:0];
                        2'b01: mem[Address[31:2]][15:8]  = DataWr[7:0];
                        2'b10: mem[Address[31:2]][23:16] = DataWr[7:0];
                        2'b11: mem[Address[31:2]][31:24] = DataWr[7:0];
                    endcase
                end

                3'b111: begin  // SH
                    case (Address[1:0])
                        2'b00: mem[Address[31:2]][15:0]  = DataWr[15:0];
                        2'b10: mem[Address[31:2]][31:16] = DataWr[15:0];
                    endcase
                end
                
                3'b011: begin  // SW
                    mem[Address[31:2]] = DataWr;
                end
            endcase
        end
    end

    // ------------------------------------------------------------
    //                      LECTURA (Load)
    // ------------------------------------------------------------
    always_comb begin
        case (DMCtrl)
            3'b000: begin  // LB
                unique case (Address[1:0])
                    2'b00: DataRd = {{24{mem[Address[31:2]][7]}},   mem[Address[31:2]][7:0]};
                    2'b01: DataRd = {{24{mem[Address[31:2]][15]}},  mem[Address[31:2]][15:8]};
                    2'b10: DataRd = {{24{mem[Address[31:2]][23]}},  mem[Address[31:2]][23:16]};
                    2'b11: DataRd = {{24{mem[Address[31:2]][31]}},  mem[Address[31:2]][31:24]};
                endcase
            end

            3'b100: begin  // LBU
                unique case (Address[1:0])
                    2'b00: DataRd = {24'b0, mem[Address[31:2]][7:0]};
                    2'b01: DataRd = {24'b0, mem[Address[31:2]][15:8]};
                    2'b10: DataRd = {24'b0, mem[Address[31:2]][23:16]};
                    2'b11: DataRd = {24'b0, mem[Address[31:2]][31:24]};
                endcase
            end

            3'b001: begin  // LH
                if (Address[1] == 1'b0)
                    DataRd = {{16{mem[Address[31:2]][15]}}, mem[Address[31:2]][15:0]};
                else
                    DataRd = {{16{mem[Address[31:2]][31]}}, mem[Address[31:2]][31:16]};
            end

            3'b101: begin  // LHU
                if (Address[1] == 1'b0)
                    DataRd = {16'b0, mem[Address[31:2]][15:0]};
                else
                    DataRd = {16'b0, mem[Address[31:2]][31:16]};
            end

            3'b010: begin  // LW
                DataRd = mem[Address[31:2]];
            end

            default: DataRd = 32'b0;
        endcase
    end

endmodule

tb/DataMemory_tb.sv
`timescale 1ns/1ps

module DataMemory_tb;

    // Señales del testbench
    logic [31:0] Address;
    logic [31:0] DataWr;
    logic        DMWr;
    logic [2:0]  DMCtrl;
    logic [31:0] DataRd;
    
    // Instancia del módulo bajo prueba
    DataMemory #(.ADDR_WIDTH(10)) uut (
        .Address(Address),
        .DataWr(DataWr),
        .DMWr(DMWr),
        .DMCtrl(DMCtrl),
        .DataRd(DataRd)
    );
    
    // Variables para verificación
    logic [31:0] expected;
    integer errors = 0;
    integer tests = 0;

    // Inicialización para wavetrace
    initial begin
        $dumpfile("sim/DataMemory_tb.vcd");
        $dumpvars(0, DataMemory_tb);
    end
    
    // Task para verificar resultado
    task check_result(input string test_name, input logic [31:0] exp);
        tests++;
        #1;
        if (DataRd !== exp) begin
            $display("ERROR: %s", test_name);
            $display("   Address:  0x%h", Address);
            $display("   DMCtrl:   0x%h (%03b)", DMCtrl, DMCtrl);
            $display("   Expected: 0x%h (%0d)", exp, exp);
            $display("   Got:      0x%h (%0d)", DataRd, DataRd);
            errors++;
        end else begin
            $display("PASS: %s", test_name);
            $display("   Address: 0x%h, DMCtrl: %03b, DataRd = 0x%h", Address, DMCtrl, DataRd);
        end
        $display("");
    endtask
    
    initial begin
        $display("\n========================================");
        $display("  DataMemory Testbench");
        $display("========================================\n");
        
        // Inicializar señales
        DMWr = 0;
        Address = 0;
        DataWr = 0;
        DMCtrl = 0;
        #10;
        
        // ==================== PRUEBAS DE ESCRITURA Y LECTURA ====================
        
        // Test 1: SW (Store Word) - Escribir palabra completa
        $display("--- Test 1: SW (Store Word) ---");
        Address = 32'h00000000;
        DataWr = 32'hDEADBEEF;
        DMCtrl = 3'b011;  // SW
        DMWr = 1;
        #10;
        DMWr = 0;
        #10;
        // Leer con LW
        DMCtrl = 3'b010;  // LW
        expected = 32'hDEADBEEF;
        #10 check_result("Test 1: LW after SW", expected);
        
        // Test 2: SB (Store Byte) - Escribir byte en offset 0
        $display("--- Test 2: SB (Store Byte) offset 0 ---");
        Address = 32'h00000004;
        DataWr = 32'h000000AB;
        DMCtrl = 3'b110;  // SB
        DMWr = 1;
        #10;
        DMWr = 0;
        #10;
        // Leer con LBU
        Address = 32'h00000004;
        DMCtrl = 3'b100;  // LBU
        expected = 32'h000000AB;
        #10 check_result("Test 2: LBU after SB at offset 0", expected);
        
        // Test 3: SB (Store Byte) - Escribir byte en offset 1
        $display("--- Test 3: SB (Store Byte) offset 1 ---");
        Address = 32'h00000005;
        DataWr = 32'h000000CD;
        DMCtrl = 3'b110;  // SB
        DMWr = 1;
        #10;
        DMWr = 0;
        #10;
        // Leer con LBU
        Address = 32'h00000005;
        DMCtrl = 3'b100;  // LBU
        expected = 32'h000000CD;
        #10 check_result("Test 3: LBU after SB at offset 1", expected);
        
        // Test 4: LB (Load Byte signed) - Byte negativo
        $display("--- Test 4: LB (Load Byte signed) ---");
        Address = 32'h00000008;
        DataWr = 32'h000000FF;  // -1 en complemento a 2
        DMCtrl = 3'b110;  // SB
        DMWr = 1;
        #10;
        DMWr = 0;
        #10;
        // Leer con LB (debe extender signo)
        Address = 32'h00000008;
        DMCtrl = 3'b000;  // LB
        expected = 32'hFFFFFFFF;  // -1 extendido
        #10 check_result("Test 4: LB signed extension", expected);
        
        // Test 5: SH (Store Halfword) - Escribir halfword en offset 0
        $display("--- Test 5: SH (Store Halfword) offset 0 ---");
        Address = 32'h0000000C;
        DataWr = 32'h00001234;
        DMCtrl = 3'b111;  // SH
        DMWr = 1;
        #10;
        DMWr = 0;
        #10;
        // Leer con LHU
        Address = 32'h0000000C;
        DMCtrl = 3'b101;  // LHU
        expected = 32'h00001234;
        #10 check_result("Test 5: LHU after SH at offset 0", expected);
        
        // Test 6: SH (Store Halfword) - Escribir halfword en offset 2
        $display("--- Test 6: SH (Store Halfword) offset 2 ---");
        Address = 32'h0000000E;
        DataWr = 32'h00005678;
        DMCtrl = 3'b111;  // SH
        DMWr = 1;
        #10;
        DMWr = 0;
        #10;
        // Leer con LHU
        Address = 32'h0000000E;
        DMCtrl = 3'b101;  // LHU
        expected = 32'h00005678;
        #10 check_result("Test 6: LHU after SH at offset 2", expected);
        
        // Test 7: LH (Load Halfword signed) - Halfword negativo
        $display("--- Test 7: LH (Load Halfword signed) ---");
        Address = 32'h00000010;
        DataWr = 32'h0000FFFF;  // -1 en 16 bits
        DMCtrl = 3'b111;  // SH
        DMWr = 1;
        #10;
        DMWr = 0;
        #10;
        // Leer con LH (debe extender signo)
        Address = 32'h00000010;
        DMCtrl = 3'b001;  // LH
        expected = 32'hFFFFFFFF;  // -1 extendido
        #10 check_result("Test 7: LH signed extension", expected);
        
        // Test 8: Verificar escritura completa de palabra con múltiples bytes
        $display("--- Test 8: Multiple byte writes forming a word ---");
        Address = 32'h00000014;
        DataWr = 32'h000000AA;
        DMCtrl = 3'b110;  // SB
        DMWr = 1;
        #10;
        Address = 32'h00000015;
        DataWr = 32'h000000BB;
        #10;
        Address = 32'h00000016;
        DataWr = 32'h000000CC;
        #10;
        Address = 32'h00000017;
        DataWr = 32'h000000DD;
        #10;
        DMWr = 0;
        #10;
        // Leer palabra completa
        Address = 32'h00000014;
        DMCtrl = 3'b010;  // LW
        expected = 32'hDDCCBBAA;  // Little-endian
        #10 check_result("Test 8: LW after multiple SB", expected);
        
        // ==================== RESUMEN ====================
        $display("========================================");
        $display("  TEST SUMMARY");
        $display("========================================");
        $display("Total tests: %0d", tests);
        $display("Passed:      %0d", tests - errors);
        $display("Failed:      %0d", errors);
        
        if (errors == 0) begin
            $display("\nALL TESTS PASSED");
        end else begin
            $display("\nSOME TESTS FAILED");
        end
        $display("========================================\n");
        
        $finish;
    end

endmodule

sim/DataMemory_tb.vcd
$date
	Mon Nov 17 21:43:17 2025
$end
$version
	Icarus Verilog
$end
$timescale
	1ps
$end
$scope module DataMemory_tb $end
$var wire 32 ! DataRd [31:0] $end
$var reg 32 " Address [31:0] $end
$var reg 3 # DMCtrl [2:0] $end
$var reg 1 $ DMWr $end
$var reg 32 % DataWr [31:0] $end
$var reg 32 & expected [31:0] $end
$var integer 32 ' errors [31:0] $end
$var integer 32 ( tests [31:0] $end
$scope module uut $end
$var wire 32 ) Address [31:0] $end
$var wire 3 * DMCtrl [2:0] $end
$var wire 1 $ DMWr $end
$var wire 32 + DataWr [31:0] $end
$var parameter 32 , ADDR_WIDTH $end
$var reg 32 - DataRd [31:0] $end
$upscope $end
$scope task check_result $end
$var reg 32 . exp [31:0] $end
$upscope $end
$upscope $end
$enddefinitions $end
$comment Show the parameter values. $end
$dumpall
b1010 ,
$end
#0
$dumpvars
bx .
bx -
b0 +
b0 *
b0 )
b0 (
b0 '
bx &
b0 %
0$
b0 #
b0 "
bx !
$end
#10000
b0 !
b0 -
1$
b11 #
b11 *
b11011110101011011011111011101111 %
b11011110101011011011111011101111 +
#20000
0$
#30000
b11011110101011011011111011101111 !
b11011110101011011011111011101111 -
b11011110101011011011111011101111 &
b10 #
b10 *
#40000
b1 (
b11011110101011011011111011101111 .
#41000
b0 !
b0 -
1$
b110 #
b110 *
b10101011 %
b10101011 +
b100 "
b100 )
#51000
0$
#61000
b10101011 !
b10101011 -
b10101011 &
b100 #
b100 *
#71000
b10 (
b10101011 .
#72000
b0 !
b0 -
1$
b110 #
b110 *
b11001101 %
b11001101 +
b101 "
b101 )
#82000
0$
#92000
b11001101 !
b11001101 -
b11001101 &
b100 #
b100 *
#102000
b11 (
b11001101 .
#103000
b0 !
b0 -
1$
b110 #
b110 *
b11111111 %
b11111111 +
b1000 "
b1000 )
#113000
0$
#123000
b11111111111111111111111111111111 !
b11111111111111111111111111111111 -
b11111111111111111111111111111111 &
b0 #
b0 *
#133000
b100 (
b11111111111111111111111111111111 .
#134000
b0 !
b0 -
1$
b111 #
b111 *
b1001000110100 %
b1001000110100 +
b1100 "
b1100 )
#144000
0$
#154000
b1001000110100 !
b1001000110100 -
b1001000110100 &
b101 #
b101 *
#164000
b101 (
b1001000110100 .
#165000
b0 !
b0 -
1$
b111 #
b111 *
b101011001111000 %
b101011001111000 +
b1110 "
b1110 )
#175000
0$
#185000
b101011001111000 !
b101011001111000 -
b101011001111000 &
b101 #
b101 *
#195000
b110 (
b101011001111000 .
#196000
b0 !
b0 -
1$
b111 #
b111 *
b1111111111111111 %
b1111111111111111 +
b10000 "
b10000 )
#206000
0$
#216000
b11111111111111111111111111111111 !
b11111111111111111111111111111111 -
b11111111111111111111111111111111 &
b1 #
b1 *
#226000
b111 (
b11111111111111111111111111111111 .
#227000
b0 !
b0 -
1$
b110 #
b110 *
b10101010 %
b10101010 +
b10100 "
b10100 )
#237000
b10111011 %
b10111011 +
b10101 "
b10101 )
#247000
b11001100 %
b11001100 +
b10110 "
b10110 )
#257000
b11011101 %
b11011101 +
b10111 "
b10111 )
#267000
0$
#277000
b11011101110011001011101110101010 !
b11011101110011001011101110101010 -
b11011101110011001011101110101010 &
b10 #
b10 *
b10100 "
b10100 )
#287000
b1000 (
b11011101110011001011101110101010 .
