src/ProgramCounter.sv
module ProgramCounter(

    input logic clk,
    input logic PCWr,
    input logic signed [31:0] PCIn,

    output logic signed [31:0] PCOut
);

    logic signed [31:0] pc_reg  = 0;

    assign PCOut = pc_reg;

    always @(posedge clk) begin
        if (PCWr) begin
            pc_reg <= PCIn;
        end 
    end

endmodule

tb/ProgramCounter_tb.sv
module ProgramCounter_tb;
    // Señales del testbench
    logic clk;
    logic PCWr;
    logic signed [31:0] PCIn;
    logic signed [31:0] PCOut;
    
    // Instanciar el DUT
    ProgramCounter dut (
        .clk(clk),
        .PCWr(PCWr),
        .PCIn(PCIn),
        .PCOut(PCOut)
    );
    
    // Generador de reloj
    initial begin
        clk = 0;
        forever #5 clk = ~clk; // Periodo de 10 unidades de tiempo
    end
    
    // Variables para verificación
    integer errors = 0;
    integer tests = 0;
    
    // Inicialización para wavetrace
    initial begin
        $dumpfile("sim/ProgramCounter_tb.vcd");
        $dumpvars(0, ProgramCounter_tb);
    end
    
    // Tarea para escribir en el PC
    task write_pc(input [31:0] value);
        @(posedge clk);
        PCIn = value;
        PCWr = 1;
        @(posedge clk);
        #1; // Pequeño delay para que se actualice
    endtask
    
    // Tarea para verificar el valor del PC
    task check_pc(input [31:0] expected, input string test_name);
        tests++;
        $display("Test: %s", test_name);
        $display("  Esperado = 0x%h (%b)", expected, expected);
        $display("  Obtenido = 0x%h (%b)", PCOut, PCOut);
        if (PCOut !== expected) begin
            $display("  ERROR: No coincide");
            errors++;
        end else begin
            $display("  OK");
        end
        $display("");
    endtask
    
    // Secuencia de pruebas
    initial begin
        // Inicialización
        PCWr = 0;
        PCIn = 0;
        
        $display("========================================");
        $display("=== Iniciando simulacion ProgramCounter ===");
        $display("========================================\n");
        
        // Esperar unos ciclos
        repeat(2) @(posedge clk);
        
        // Test 1: Verificar inicialización
        $display("========== Test 1: Verificar inicializacion ==========");
        check_pc(32'h00000000, "PC inicial debe ser 0");
        
        // Test 2: Escribir primera dirección
        $display("========== Test 2: Escribir primera direccion ==========");
        write_pc(32'h00000004);
        PCWr = 0;
        check_pc(32'h00000004, "PC = 0x00000004");
        
        // Test 3: Incremento típico de PC (siguiente instrucción)
        $display("========== Test 3: Incremento tipico PC +4 ==========");
        write_pc(32'h00000008);
        PCWr = 0;
        check_pc(32'h00000008, "PC = 0x00000008");
        
        write_pc(32'h0000000C);
        PCWr = 0;
        check_pc(32'h0000000C, "PC = 0x0000000C");
        
        // Test 4: PC no debe cambiar sin PCWr
        $display("========== Test 4: PC no cambia sin PCWr ==========");
        @(posedge clk);
        PCIn = 32'hDEADBEEF;
        PCWr = 0; // No activado
        @(posedge clk);
        #1;
        check_pc(32'h0000000C, "PC debe mantener valor anterior");
        
        // Test 5: Salto a dirección arbitraria
        $display("========== Test 5: Salto a direccion arbitraria ==========");
        write_pc(32'h00001000);
        PCWr = 0;
        check_pc(32'h00001000, "PC = 0x00001000");
        
        // Test 6: Salto hacia atrás (negativo)
        $display("========== Test 6: Salto hacia atras ==========");
        write_pc(32'h00000100);
        PCWr = 0;
        check_pc(32'h00000100, "PC = 0x00000100");
        
        // Test 7: Mantener PC durante varios ciclos
        $display("========== Test 7: Mantener PC sin cambios ==========");
        PCWr = 0;
        repeat(5) @(posedge clk);
        #1;
        check_pc(32'h00000100, "PC debe mantenerse en 0x00000100");
        
        // Test 8: Secuencia de saltos rápidos
        $display("========== Test 8: Secuencia de saltos rapidos ==========");
        write_pc(32'h00002000);
        PCWr = 0;
        check_pc(32'h00002000, "PC = 0x00002000");
        
        write_pc(32'h00003000);
        PCWr = 0;
        check_pc(32'h00003000, "PC = 0x00003000");
        
        write_pc(32'h00004000);
        PCWr = 0;
        check_pc(32'h00004000, "PC = 0x00004000");
        
        // Test 9: Escribir con PCWr mantenido activo
        $display("========== Test 9: PCWr mantenido activo ==========");
        @(posedge clk);
        PCIn = 32'h00005000;
        PCWr = 1;
        @(posedge clk);
        PCIn = 32'h00006000;
        // PCWr sigue activo
        @(posedge clk);
        #1;
        PCWr = 0;
        check_pc(32'h00006000, "PC debe actualizar a ultimo valor");
        
        // Test 10: Reset a dirección 0
        $display("========== Test 10: Reset a direccion 0 ==========");
        write_pc(32'h00000000);
        PCWr = 0;
        check_pc(32'h00000000, "PC = 0x00000000");
        
        // Test 11: Valores grandes
        $display("========== Test 11: Valores grandes ==========");
        write_pc(32'hFFFFFFFC);
        PCWr = 0;
        check_pc(32'hFFFFFFFC, "PC = 0xFFFFFFFC");
        
        // Test 12: Simulación de bucle (PC cambia múltiples veces)
        $display("========== Test 12: Simulacion de bucle ==========");
        write_pc(32'h00000200);
        PCWr = 0;
        check_pc(32'h00000200, "PC = 0x00000200");
        
        write_pc(32'h00000204);
        PCWr = 0;
        check_pc(32'h00000204, "PC = 0x00000204");
        
        write_pc(32'h00000208);
        PCWr = 0;
        check_pc(32'h00000208, "PC = 0x00000208");
        
        write_pc(32'h00000200); // Volver al inicio del bucle
        PCWr = 0;
        check_pc(32'h00000200, "PC = 0x00000200 (vuelta al inicio)");
        
        // Resumen final
        $display("========================================");
        $display("=== Resumen de la simulacion ===");
        $display("Tests ejecutados: %0d", tests);
        $display("Tests exitosos: %0d", tests - errors);
        $display("Errores: %0d", errors);
        $display("========================================");
        
        if (errors == 0)
            $display("Todos los tests pasaron exitosamente");
        else
            $display("Se encontraron %0d errores", errors);
        
        // Finalizar simulación
        repeat(3) @(posedge clk);
        $finish;
    end
    
endmodule

sim/ProgramCounter_tb.vcd
$date
	Wed Oct 29 21:54:16 2025
$end
$version
	Icarus Verilog
$end
$timescale
	1s
$end
$scope module ProgramCounter_tb $end
$var wire 32 ! PCOut [31:0] $end
$var reg 32 " PCIn [31:0] $end
$var reg 1 # PCWr $end
$var reg 1 $ clk $end
$var integer 32 % errors [31:0] $end
$var integer 32 & tests [31:0] $end
$scope module dut $end
$var wire 32 ' PCIn [31:0] $end
$var wire 32 ( PCOut [31:0] $end
$var wire 1 # PCWr $end
$var wire 1 $ clk $end
$var reg 32 ) pc_reg [31:0] $end
$upscope $end
$scope task check_pc $end
$var reg 32 * expected [31:0] $end
$upscope $end
$scope task write_pc $end
$var reg 32 + value [31:0] $end
$upscope $end
$upscope $end
$enddefinitions $end
$comment Show the parameter values. $end
$dumpall
$end
#0
$dumpvars
bx +
bx *
b0 )
b0 (
b0 '
b0 &
b0 %
0$
0#
b0 "
b0 !
$end
#5
1$
#10
0$
#15
b100 +
b1 &
b0 *
1$
#20
0$
#25
b100 !
b100 (
b100 )
1#
b100 "
b100 '
1$
#30
0$
#35
1$
#36
b1000 +
b10 &
b100 *
0#
#40
0$
#45
b1000 !
b1000 (
b1000 )
1#
b1000 "
b1000 '
1$
#50
0$
#55
1$
#56
b1100 +
b11 &
b1000 *
0#
#60
0$
#65
b1100 !
b1100 (
b1100 )
1#
b1100 "
b1100 '
1$
#70
0$
#75
1$
#76
b100 &
b1100 *
0#
#80
0$
#85
b11011110101011011011111011101111 "
b11011110101011011011111011101111 '
1$
#90
0$
#95
1$
#96
b1000000000000 +
b101 &
#100
0$
#105
b1000000000000 !
b1000000000000 (
b1000000000000 )
1#
b1000000000000 "
b1000000000000 '
1$
#110
0$
#115
1$
#116
b100000000 +
b110 &
b1000000000000 *
0#
#120
0$
#125
b100000000 !
b100000000 (
b100000000 )
1#
b100000000 "
b100000000 '
1$
#130
0$
#135
1$
#136
b111 &
b100000000 *
0#
#140
0$
#145
1$
#150
0$
#155
1$
#160
0$
#165
1$
#170
0$
#175
1$
#180
0$
#185
1$
#186
b10000000000000 +
b1000 &
#190
0$
#195
b10000000000000 !
b10000000000000 (
b10000000000000 )
1#
b10000000000000 "
b10000000000000 '
1$
#200
0$
#205
1$
#206
b11000000000000 +
b1001 &
b10000000000000 *
0#
#210
0$
#215
b11000000000000 !
b11000000000000 (
b11000000000000 )
1#
b11000000000000 "
b11000000000000 '
1$
#220
0$
#225
1$
#226
b100000000000000 +
b1010 &
b11000000000000 *
0#
#230
0$
#235
b100000000000000 !
b100000000000000 (
b100000000000000 )
1#
b100000000000000 "
b100000000000000 '
1$
#240
0$
#245
1$
#246
b1011 &
b100000000000000 *
0#
#250
0$
#255
b101000000000000 !
b101000000000000 (
b101000000000000 )
1#
b101000000000000 "
b101000000000000 '
1$
#260
0$
#265
b110000000000000 "
b110000000000000 '
1$
#270
0$
#275
b110000000000000 !
b110000000000000 (
b110000000000000 )
1$
#276
b0 +
b1100 &
b110000000000000 *
0#
#280
0$
#285
b0 !
b0 (
b0 )
1#
b0 "
b0 '
1$
#290
0$
#295
1$
#296
b11111111111111111111111111111100 +
b1101 &
b0 *
0#
#300
0$
#305
b11111111111111111111111111111100 !
b11111111111111111111111111111100 (
b11111111111111111111111111111100 )
1#
b11111111111111111111111111111100 "
b11111111111111111111111111111100 '
1$
#310
0$
#315
1$
#316
b1000000000 +
b1110 &
b11111111111111111111111111111100 *
0#
#320
0$
#325
b1000000000 !
b1000000000 (
b1000000000 )
1#
b1000000000 "
b1000000000 '
1$
#330
0$
#335
1$
#336
b1000000100 +
b1111 &
b1000000000 *
0#
#340
0$
#345
b1000000100 !
b1000000100 (
b1000000100 )
1#
b1000000100 "
b1000000100 '
1$
#350
0$
#355
1$
#356
b1000001000 +
b10000 &
b1000000100 *
0#
#360
0$
#365
b1000001000 !
b1000001000 (
b1000001000 )
1#
b1000001000 "
b1000001000 '
1$
#370
0$
#375
1$
#376
b1000000000 +
b10001 &
b1000001000 *
0#
#380
0$
#385
b1000000000 !
b1000000000 (
b1000000000 )
1#
b1000000000 "
b1000000000 '
1$
#390
0$
#395
1$
#396
b10010 &
b1000000000 *
0#
