src/RegistersUnit.sv
module RegistersUnit(

    input logic clk,
    input logic signed [4:0] rs1,
    input logic signed [4:0] rs2,
    input logic signed [4:0] rd,

    input logic signed [31:0] DataWR,
    input logic RUWr, // toggle

    output logic signed [31:0] ru_rs1,
    output logic signed [31:0] ru_rs2
);
    // register matrix
    logic signed [31:0] ru [31:0];

    initial begin
        integer i;
        for (i = 0; i < 32; i++) begin
            ru[i] = 32'b0;    // inicializa todos los registros en 0
        end
        ru[2] = 32'b1000000000;
    end

    assign ru_rs1 = ru[rs1];
    assign ru_rs2 = ru[rs2];

    always @(posedge clk) begin
        if (RUWr && rd != 0) begin
            ru[rd] <= DataWR;
        end 
    end
endmodule

tb/RegistersUnit_tb.sv
module RegistersUnit_tb;
    // Señales del testbench
    logic clk;
    logic signed [4:0] rs1;
    logic signed [4:0] rs2;
    logic signed [4:0] rd;
    logic signed [31:0] DataWR;
    logic RUWr;
    logic signed [31:0] ru_rs1;
    logic signed [31:0] ru_rs2;
    
    // Instanciar el DUT
    RegistersUnit dut (
        .clk(clk),
        .rs1(rs1),
        .rs2(rs2),
        .rd(rd),
        .DataWR(DataWR),
        .RUWr(RUWr),
        .ru_rs1(ru_rs1),
        .ru_rs2(ru_rs2)
    );
    
    // Generador de reloj
    initial begin
        clk = 0;
        forever #5 clk = ~clk; // Periodo de 10 unidades de tiempo
    end
    
    // Variables para verificación
    integer errors = 0;
    integer tests = 0;
    
    // Inicialización para wavetrace
    initial begin
        $dumpfile("sim/RegistersUnit_tb.vcd");
        $dumpvars(0, RegistersUnit_tb);
    end
    
    // Tarea para escribir en un registro
    task write_register(input [4:0] reg_addr, input [31:0] data);
        @(posedge clk);
        rd = reg_addr;
        DataWR = data;
        RUWr = 1;
        @(posedge clk);
        RUWr = 0;
        $display("Escritura: R%0d = 0x%h (%b)", reg_addr, data, data);
    endtask
    
    // Tarea para leer y verificar un registro
    task read_register(input [4:0] reg_addr, input [31:0] expected);
        @(posedge clk);
        rs1 = reg_addr;
        #1; // Pequeño delay para que se propague la lectura
        tests++;
        $display("Lectura R%0d:", reg_addr);
        $display("  Esperado = 0x%h (%b)", expected, expected);
        $display("  Obtenido = 0x%h (%b)", ru_rs1, ru_rs1);
        if (ru_rs1 !== expected) begin
            $display("  ERROR: No coincide");
            errors++;
        end else begin
            $display("  OK");
        end
        $display("");
    endtask
    
    // Tarea para leer dos registros simultáneamente
    task read_two_registers(input [4:0] reg1, input [4:0] reg2, 
                           input [31:0] exp1, input [31:0] exp2);
        @(posedge clk);
        rs1 = reg1;
        rs2 = reg2;
        #1;
        tests += 2;
        $display("Lectura simultanea R%0d y R%0d:", reg1, reg2);
        $display("  R%0d: Esperado = 0x%h, Obtenido = 0x%h", reg1, exp1, ru_rs1);
        if (ru_rs1 !== exp1) begin
            $display("       ERROR en R%0d", reg1);
            errors++;
        end else begin
            $display("       OK R%0d", reg1);
        end
        
        $display("  R%0d: Esperado = 0x%h, Obtenido = 0x%h", reg2, exp2, ru_rs2);
        if (ru_rs2 !== exp2) begin
            $display("       ERROR en R%0d", reg2);
            errors++;
        end else begin
            $display("       OK R%0d", reg2);
        end
        $display("");
    endtask
    
    // Secuencia de pruebas
    initial begin
        // Inicialización
        rs1 = 0;
        rs2 = 0;
        rd = 0;
        DataWR = 0;
        RUWr = 0;
        
        $display("========================================");
        $display("=== Iniciando simulacion RegistersUnit ===");
        $display("========================================\n");
        
        // Esperar unos ciclos
        repeat(3) @(posedge clk);
        
        // Test 1: Verificar inicialización de R2
        $display("========== Test 1: Verificar inicializacion ==========");
        read_register(2, 32'h00000200); // R2 debe inicializarse con 1000000000 binario = 0x200
        
        // Test 2: Verificar que R0 siempre es 0
        $display("========== Test 2: Verificar R0 siempre es 0 ==========");
        read_register(0, 32'h00000000);
        
        // Test 3: Intentar escribir en R0 (debe fallar, R0 siempre es 0)
        $display("========== Test 3: Intentar escribir en R0 ==========");
        write_register(0, 32'hDEADBEEF);
        read_register(0, 32'h00000000); // Debe seguir siendo 0
        
        // Test 4: Escribir valores en varios registros
        $display("========== Test 4: Escribir en registros ==========");
        write_register(1, 32'h0000000A);  // R1 = 10
        write_register(3, 32'h00000014);  // R3 = 20
        write_register(5, 32'hFFFFFFFF);  // R5 = -1
        write_register(10, 32'h12345678); // R10 = 0x12345678
        
        // Test 5: Leer los valores escritos
        $display("========== Test 5: Leer valores escritos ==========");
        read_register(1, 32'h0000000A);
        read_register(3, 32'h00000014);
        read_register(5, 32'hFFFFFFFF);
        read_register(10, 32'h12345678);
        
        // Test 6: Sobrescribir un registro
        $display("========== Test 6: Sobrescribir registro ==========");
        $display("Escribiendo nuevo valor en R1");
        write_register(1, 32'h000000FF);
        read_register(1, 32'h000000FF);
        
        // Test 7: Lecturas simultáneas
        $display("========== Test 7: Lecturas simultaneas ==========");
        read_two_registers(1, 3, 32'h000000FF, 32'h00000014);
        read_two_registers(5, 10, 32'hFFFFFFFF, 32'h12345678);
        
        // Test 8: Escribir sin RUWr activado
        $display("========== Test 8: Escribir sin RUWr (no debe escribir) ==========");
        @(posedge clk);
        rd = 7;
        DataWR = 32'hBAADF00D;
        RUWr = 0; // No activado
        @(posedge clk);
        $display("Intento de escritura en R7 sin RUWr");
        read_register(7, 32'h00000000); // Debe seguir en 0
        
        // Test 9: Escribir y leer en el mismo ciclo
        $display("========== Test 9: Escribir en R15 ==========");
        write_register(15, 32'hCAFEBABE);
        read_register(15, 32'hCAFEBABE);
        
        // Test 10: Probar registros en los límites
        $display("========== Test 10: Registros en los limites ==========");
        write_register(31, 32'hFFFF0000);
        read_register(31, 32'hFFFF0000);
        
        // Test 11: Valores negativos
        $display("========== Test 11: Valores negativos ==========");
        write_register(20, 32'hFFFFFFF0); // -16 en complemento a 2
        read_register(20, 32'hFFFFFFF0);
        
        // Resumen final
        $display("========================================");
        $display("=== Resumen de la simulacion ===");
        $display("Tests ejecutados: %0d", tests);
        $display("Tests exitosos: %0d", tests - errors);
        $display("Errores: %0d", errors);
        $display("========================================");
        
        if (errors == 0)
            $display("Todos los tests pasaron exitosamente");
        else
            $display("Se encontraron %0d errores", errors);
        
        // Finalizar simulación
        repeat(5) @(posedge clk);
        $finish;
    end
    
endmodule

sim/RegistersUnit_tb.vcd
$date
	Tue Oct 28 17:15:54 2025
$end
$version
	Icarus Verilog
$end
$timescale
	1s
$end
$scope module RegistersUnit_tb $end
$var wire 32 ! ru_rs2 [31:0] $end
$var wire 32 " ru_rs1 [31:0] $end
$var reg 32 # DataWR [31:0] $end
$var reg 1 $ RUWr $end
$var reg 1 % clk $end
$var reg 5 & rd [4:0] $end
$var reg 5 ' rs1 [4:0] $end
$var reg 5 ( rs2 [4:0] $end
$var integer 32 ) errors [31:0] $end
$var integer 32 * tests [31:0] $end
$scope module dut $end
$var wire 32 + DataWR [31:0] $end
$var wire 1 $ RUWr $end
$var wire 1 % clk $end
$var wire 5 , rd [4:0] $end
$var wire 5 - rs1 [4:0] $end
$var wire 5 . rs2 [4:0] $end
$var wire 32 / ru_rs1 [31:0] $end
$var wire 32 0 ru_rs2 [31:0] $end
$scope begin $unm_blk_10 $end
$var integer 32 1 i [31:0] $end
$upscope $end
$upscope $end
$scope task read_register $end
$var reg 32 2 expected [31:0] $end
$var reg 5 3 reg_addr [4:0] $end
$upscope $end
$scope task read_two_registers $end
$var reg 32 4 exp1 [31:0] $end
$var reg 32 5 exp2 [31:0] $end
$var reg 5 6 reg1 [4:0] $end
$var reg 5 7 reg2 [4:0] $end
$upscope $end
$scope task write_register $end
$var reg 32 8 data [31:0] $end
$var reg 5 9 reg_addr [4:0] $end
$upscope $end
$upscope $end
$enddefinitions $end
$comment Show the parameter values. $end
$dumpall
$end
#0
$dumpvars
bx 9
bx 8
bx 7
bx 6
bx 5
bx 4
bx 3
bx 2
b100000 1
b0 0
b0 /
b0 .
b0 -
b0 ,
b0 +
b0 *
b0 )
b0 (
b0 '
b0 &
0%
0$
b0 #
b0 "
b0 !
$end
#5
1%
#10
0%
#15
1%
#20
0%
#25
b1000000000 2
b10 3
1%
#30
0%
#35
b1000000000 "
b1000000000 /
b10 '
b10 -
1%
#36
b0 2
b0 3
b1 *
#40
0%
#45
b0 "
b0 /
b0 '
b0 -
1%
#46
b11011110101011011011111011101111 8
b0 9
b10 *
#50
0%
#55
1$
b11011110101011011011111011101111 #
b11011110101011011011111011101111 +
1%
#60
0%
#65
0$
1%
#70
0%
#75
1%
#76
b1010 8
b1 9
b11 *
#80
0%
#85
1$
b1010 #
b1010 +
b1 &
b1 ,
1%
#90
0%
#95
b10100 8
b11 9
0$
1%
#100
0%
#105
1$
b10100 #
b10100 +
b11 &
b11 ,
1%
#110
0%
#115
b11111111111111111111111111111111 8
b101 9
0$
1%
#120
0%
#125
1$
b11111111111111111111111111111111 #
b11111111111111111111111111111111 +
b101 &
b101 ,
1%
#130
0%
#135
b10010001101000101011001111000 8
b1010 9
0$
1%
#140
0%
#145
1$
b10010001101000101011001111000 #
b10010001101000101011001111000 +
b1010 &
b1010 ,
1%
#150
0%
#155
b1010 2
b1 3
0$
1%
#160
0%
#165
b1010 "
b1010 /
b1 '
b1 -
1%
#166
b10100 2
b11 3
b100 *
#170
0%
#175
b10100 "
b10100 /
b11 '
b11 -
1%
#176
b11111111111111111111111111111111 2
b101 3
b101 *
#180
0%
#185
b11111111111111111111111111111111 "
b11111111111111111111111111111111 /
b101 '
b101 -
1%
#186
b10010001101000101011001111000 2
b1010 3
b110 *
#190
0%
#195
b10010001101000101011001111000 "
b10010001101000101011001111000 /
b1010 '
b1010 -
1%
#196
b11111111 8
b1 9
b111 *
#200
0%
#205
1$
b11111111 #
b11111111 +
b1 &
b1 ,
1%
#210
0%
#215
b11111111 2
b1 3
0$
1%
#220
0%
#225
b11111111 "
b11111111 /
b1 '
b1 -
1%
#226
b10100 5
b11111111 4
b11 7
b1 6
b1000 *
#230
0%
#235
b10100 !
b10100 0
b11 (
b11 .
1%
#236
b10010001101000101011001111000 5
b11111111111111111111111111111111 4
b1010 7
b101 6
b1010 *
#240
0%
#245
b10010001101000101011001111000 !
b10010001101000101011001111000 0
b1010 (
b1010 .
b11111111111111111111111111111111 "
b11111111111111111111111111111111 /
b101 '
b101 -
1%
#246
b1100 *
#250
0%
#255
b10111010101011011111000000001101 #
b10111010101011011111000000001101 +
b111 &
b111 ,
1%
#260
0%
#265
b0 2
b111 3
1%
#270
0%
#275
b0 "
b0 /
b111 '
b111 -
1%
#276
b11001010111111101011101010111110 8
b1111 9
b1101 *
#280
0%
#285
1$
b11001010111111101011101010111110 #
b11001010111111101011101010111110 +
b1111 &
b1111 ,
1%
#290
0%
#295
b11001010111111101011101010111110 2
b1111 3
0$
1%
#300
0%
#305
b11001010111111101011101010111110 "
b11001010111111101011101010111110 /
b1111 '
b1111 -
1%
#306
b11111111111111110000000000000000 8
b11111 9
b1110 *
#310
0%
#315
1$
b11111111111111110000000000000000 #
b11111111111111110000000000000000 +
b11111 &
b11111 ,
1%
#320
0%
#325
b11111111111111110000000000000000 2
b11111 3
0$
1%
#330
0%
#335
bx "
bx /
b11111 '
b11111 -
1%
#336
b11111111111111111111111111110000 8
b10100 9
b1 )
b1111 *
#340
0%
#345
1$
b11111111111111111111111111110000 #
b11111111111111111111111111110000 +
b10100 &
b10100 ,
1%
#350
0%
#355
b11111111111111111111111111110000 2
b10100 3
0$
1%
#360
0%
#365
b10100 '
b10100 -
1%
#366
b10 )
b10000 *
