src/RUDataWrSrcMux.sv
module RUDataWrSrcMux(
    input logic signed [31:0] alu_result,
    input logic signed [31:0] data_mem_rd,
    input logic signed [31:0] adder_result,
    input logic signed [1:0] sel,

    output logic signed [31:0] ru_wrdata
);
    always @(*) begin
        if (sel == 2'b10)
            ru_wrdata = adder_result;
        else if (sel == 2'b01)
            ru_wrdata = data_mem_rd;
        else
            ru_wrdata = alu_result;
    end
endmodule

tb/RUDataWrSrcMux_tb.sv
module RUDataWrSrcMux_tb;
    // Señales del testbench
    logic signed [31:0] alu_result;
    logic signed [31:0] data_mem_rd;
    logic signed [31:0] adder_result;
    logic signed [1:0] sel;
    logic signed [31:0] ru_wrdata;
    
    // Instanciar el DUT
    RUDataWrSrcMux dut (
        .alu_result(alu_result),
        .data_mem_rd(data_mem_rd),
        .adder_result(adder_result),
        .sel(sel),
        .ru_wrdata(ru_wrdata)
    );
    
    // Variables para verificación
    integer errors = 0;
    integer tests = 0;
    
    // Inicialización para wavetrace
    initial begin
        $dumpfile("sim/RUDataWrSrcMux_tb.vcd");
        $dumpvars(0, RUDataWrSrcMux_tb);
    end
    
    // Tarea para verificar resultado
    task check_result(input [31:0] alu_val, input [31:0] mem_val, 
                     input [31:0] adder_val, input [1:0] sel_val,
                     input [31:0] expected, input string test_name);
        tests++;
        alu_result = alu_val;
        data_mem_rd = mem_val;
        adder_result = adder_val;
        sel = sel_val;
        #10; // Esperar a que se propague
        $display("Test %0d: %s", tests, test_name);
        $display("  alu_result    = 0x%h", alu_val);
        $display("  data_mem_rd   = 0x%h", mem_val);
        $display("  adder_result  = 0x%h", adder_val);
        $display("  SEL           = %b (%s)", sel_val, 
                 sel_val == 2'b10 ? "adder_result" : 
                 sel_val == 2'b01 ? "data_mem_rd" : "alu_result");
        $display("  Esperado      = 0x%h", expected);
        $display("  Obtenido      = 0x%h", ru_wrdata);
        if (ru_wrdata !== expected) begin
            $display("  ERROR: No coincide");
            errors++;
        end else begin
            $display("  OK");
        end
        $display("");
    endtask
    
    // Secuencia de pruebas
    initial begin
        alu_result = 0;
        data_mem_rd = 0;
        adder_result = 0;
        sel = 0;
        
        $display("========================================");
        $display("=== Iniciando simulacion RUDataWrSrcMux ===");
        $display("========================================\n");
        
        #10;
        
        // Test 1: Seleccionar alu_result (sel=00)
        $display("========== Test 1: Seleccionar alu_result (sel=00) ==========");
        check_result(32'h0000002A, 32'h00000064, 32'h00000100, 2'b00, 
                    32'h0000002A, "Usar alu_result");
        
        // Test 2: Seleccionar data_mem_rd (sel=01)
        $display("========== Test 2: Seleccionar data_mem_rd (sel=01) ==========");
        check_result(32'h0000002A, 32'h00000064, 32'h00000100, 2'b01, 
                    32'h00000064, "Usar data_mem_rd");
        
        // Test 3: Seleccionar adder_result (sel=10)
        $display("========== Test 3: Seleccionar adder_result (sel=10) ==========");
        check_result(32'h0000002A, 32'h00000064, 32'h00000100, 2'b10, 
                    32'h00000100, "Usar adder_result");
        
        // Test 4: Seleccionar alu_result con sel=11 (default)
        $display("========== Test 4: sel=11 debe usar alu_result (default) ==========");
        check_result(32'h12345678, 32'hABCDEF00, 32'hDEADBEEF, 2'b11, 
                    32'h12345678, "Default a alu_result");
        
        // Test 5: data_mem_rd con valor negativo (sel=01)
        $display("========== Test 5: data_mem_rd negativo ==========");
        check_result(32'h00000050, 32'hFFFFFFF0, 32'h00000200, 2'b01, 
                    32'hFFFFFFF0, "Usar data_mem_rd negativo");
        
        // Test 6: adder_result con PC+4 típico (sel=10)
        $display("========== Test 6: adder_result PC+4 ==========");
        check_result(32'h00000000, 32'h00000000, 32'h00000104, 2'b10, 
                    32'h00000104, "Usar adder_result PC+4");
        
        // Test 7: alu_result con valor grande (sel=00)
        $display("========== Test 7: alu_result valor grande ==========");
        check_result(32'h7FFFFFFF, 32'h00001000, 32'h00002000, 2'b00, 
                    32'h7FFFFFFF, "Usar alu_result grande");
        
        // Test 8: Todos cero con sel=01
        $display("========== Test 8: Todos cero, seleccionar data_mem_rd ==========");
        check_result(32'h00000000, 32'h00000000, 32'h00000000, 2'b01, 
                    32'h00000000, "Todos cero");
        
        // Resumen final
        $display("========================================");
        $display("=== Resumen de la simulacion ===");
        $display("Tests ejecutados: %0d", tests);
        $display("Tests exitosos: %0d", tests - errors);
        $display("Errores: %0d", errors);
        $display("========================================");
        
        if (errors == 0)
            $display("Todos los tests pasaron exitosamente");
        else
            $display("Se encontraron %0d errores", errors);
        
        $finish;
    end
    
endmodule

sim/RUDataWrSrcMux_tb.vcd
$date
	Wed Oct 29 23:53:59 2025
$end
$version
	Icarus Verilog
$end
$timescale
	1s
$end
$scope module RUDataWrSrcMux_tb $end
$var wire 32 ! ru_wrdata [31:0] $end
$var reg 32 " adder_result [31:0] $end
$var reg 32 # alu_result [31:0] $end
$var reg 32 $ data_mem_rd [31:0] $end
$var reg 2 % sel [1:0] $end
$var integer 32 & errors [31:0] $end
$var integer 32 ' tests [31:0] $end
$scope module dut $end
$var wire 32 ( adder_result [31:0] $end
$var wire 32 ) alu_result [31:0] $end
$var wire 32 * data_mem_rd [31:0] $end
$var wire 2 + sel [1:0] $end
$var reg 32 , ru_wrdata [31:0] $end
$upscope $end
$scope task check_result $end
$var reg 32 - adder_val [31:0] $end
$var reg 32 . alu_val [31:0] $end
$var reg 32 / expected [31:0] $end
$var reg 32 0 mem_val [31:0] $end
$var reg 2 1 sel_val [1:0] $end
$upscope $end
$upscope $end
$enddefinitions $end
$comment Show the parameter values. $end
$dumpall
$end
#0
$dumpvars
bx 1
bx 0
bx /
bx .
bx -
b0 ,
b0 +
b0 *
b0 )
b0 (
b0 '
b0 &
b0 %
b0 $
b0 #
b0 "
b0 !
$end
#10
b101010 !
b101010 ,
b100000000 "
b100000000 (
b1100100 $
b1100100 *
b101010 #
b101010 )
b1 '
b101010 /
b0 1
b100000000 -
b1100100 0
b101010 .
#20
b1100100 !
b1100100 ,
b1 %
b1 +
b10 '
b1100100 /
b1 1
#30
b100000000 !
b100000000 ,
b10 %
b10 +
b11 '
b100000000 /
b10 1
#40
b10010001101000101011001111000 !
b10010001101000101011001111000 ,
b11 %
b11 +
b11011110101011011011111011101111 "
b11011110101011011011111011101111 (
b10101011110011011110111100000000 $
b10101011110011011110111100000000 *
b10010001101000101011001111000 #
b10010001101000101011001111000 )
b100 '
b10010001101000101011001111000 /
b11 1
b11011110101011011011111011101111 -
b10101011110011011110111100000000 0
b10010001101000101011001111000 .
#50
b11111111111111111111111111110000 !
b11111111111111111111111111110000 ,
b1 %
b1 +
b1000000000 "
b1000000000 (
b11111111111111111111111111110000 $
b11111111111111111111111111110000 *
b1010000 #
b1010000 )
b101 '
b11111111111111111111111111110000 /
b1 1
b1000000000 -
b11111111111111111111111111110000 0
b1010000 .
#60
b100000100 !
b100000100 ,
b10 %
b10 +
b100000100 "
b100000100 (
b0 $
b0 *
b0 #
b0 )
b110 '
b100000100 /
b10 1
b100000100 -
b0 0
b0 .
#70
b1111111111111111111111111111111 !
b1111111111111111111111111111111 ,
b0 %
b0 +
b10000000000000 "
b10000000000000 (
b1000000000000 $
b1000000000000 *
b1111111111111111111111111111111 #
b1111111111111111111111111111111 )
b111 '
b1111111111111111111111111111111 /
b0 1
b10000000000000 -
b1000000000000 0
b1111111111111111111111111111111 .
#80
b0 !
b0 ,
b1 %
b1 +
b0 "
b0 (
b0 $
b0 *
b0 #
b0 )
b1000 '
b0 /
b1 1
b0 -
b0 0
b0 .
